dtlpymcp/__init__.py
dtlpymcp/__main__.py
dtlpymcp/min_proxy.py
dtlpymcp/proxy.py
dtlpymcp/utils/dtlpy_context.py
dtlpymcp-0.1.13.dist-info/METADATA
dtlpymcp-0.1.13.dist-info/WHEEL
dtlpymcp-0.1.13.dist-info/entry_points.txt
dtlpymcp-0.1.13.dist-info/top_level.txt
dtlpymcp-0.1.13.dist-info/RECORD
