Metadata-Version: 2.4
Name: dtlpymcp
Version: 0.1.13
Summary: STDIO MCP proxy server for Dataloop platform.
Author-email: Your Name <your.email@example.com>
Classifier: Programming Language :: Python :: 3.10
Classifier: License :: OSI Approved :: MIT License
Classifier: Operating System :: OS Independent
Requires-Python: >=3.10
Requires-Dist: dtlpy
Requires-Dist: pydantic-settings
Requires-Dist: mcp
Requires-Dist: requests
Requires-Dist: pyjwt
Requires-Dist: makefun
